eon4injuries/Skadetabell.py
eon4injuries/__init__.py
eon4injuries/injuries.py
eon4injuries/skadetabell.txt
eon4injuries-1.0.2.3.dist-info/LICENSE
eon4injuries-1.0.2.3.dist-info/METADATA
eon4injuries-1.0.2.3.dist-info/WHEEL
eon4injuries-1.0.2.3.dist-info/top_level.txt
eon4injuries-1.0.2.3.dist-info/RECORD
