Metadata-Version: 2.1
Name: eon4injuries
Version: 1.0.2.3
Summary: A library that generates injuries for the Swedish roleplaying game EON IV (https://helmgast.se/eon/).
Author-email: Oliver Glant <oliver.glant@gmail.com>
Project-URL: Homepage, https://github.com/Leopaexd/eon4injuries
Project-URL: Bug Tracker, https://github.com/Leopaexd/eon4injuries/issues
Classifier: Programming Language :: Python :: 3
Classifier: License :: OSI Approved :: MIT License
Classifier: Operating System :: OS Independent
Requires-Python: >=3.7
License-File: LICENSE
Requires-Dist: eon4dice
